crm114
