Metadata-Version: 1.1
Name: crm114
Version: 2.0.1
Summary: Python wrapper classes for the CRM-114 Discriminator (http://crm114.sourceforge.net/)
Home-page: http://packages.python.org/crm114
Author: Brian Cline
Author-email: brian.cline@gmail.com
License: MIT
Keywords: crm114 text analysis classifier
Platform: UNKNOWN
Classifier: Development Status :: 3 - Alpha
Classifier: License :: OSI Approved :: MIT License
Classifier: Intended Audience :: Developers
Classifier: Intended Audience :: Science/Research
Classifier: Natural Language :: English
Classifier: Operating System :: POSIX :: Linux
Classifier: Programming Language :: Python
Classifier: Programming Language :: Python :: 2.7
Classifier: Topic :: Adaptive Technologies
Classifier: Topic :: Scientific/Engineering :: Artificial Intelligence
Classifier: Topic :: Scientific/Engineering :: Information Analysis
Classifier: Topic :: Software Development :: Libraries :: Python Modules
Classifier: Topic :: Text Processing
